setup.py
Java/__init__.py
Java/world.py
Javaworld.egg-info/PKG-INFO
Javaworld.egg-info/SOURCES.txt
Javaworld.egg-info/dependency_links.txt
Javaworld.egg-info/top_level.txt